{
    "menu": {
        "about": "درباره من",
        "skills": "مهارت ها",
        "projects": "پروژه ها"
    },
    "hero": {
        "name": "بهاره",
        "family": "غلامی",
        "proficiency": "توسعه دهنده فرانت اند",
        "discription": "توسعه‌دهنده فرانت‌اند با تمرکز بر Next.js، React و TypeScript. در حال حاضر به دنبال فرصت کارآموزی برای کسب تجربه در دنیای واقعی و مشارکت در پروژه‌های معنادار هستم."
    },
    "about": {
        "heading": "درباره من",
        "education": {
            "heading": "تحصیلات",
            "degree": "کارشناسی مهندسی نرم افزار",
            "uni": "دانشگاه رجا - خرداد 1395",
            "project": {
                "title": "پروژه پایانی",
                "name": "برنماه مدیریت آموزشگاه زبان",
                "tech": "تکنولوژی ها",
                "techs": "C#, Windows Forms, SQL Server",
                "disTitle": "توضیحات",
                "discription": "یک اپلیکیشن دسکتاپ برای مدیریت کلاس‌ها و دانش‌آموزان در آموزشگاه‌های زبان که شامل مدیریت دوره‌ها و گزارش‌گیری پایه بود."
            }
        },
        "courses": {
            "heading": "دوره ها",
            "title": "دوره آنلاین طراحی محصول دیجیتال",
            "academy": "آکادامی آمانج - تیر 1401",
            "discription": "در این دوره طراحی محصول یاد گرفتم که ساخت یک محصول موفق فقط به حل یک مسئله محدود نمی‌شود، بلکه خلق تجربه‌ای لذت‌بخش است که منجر میشود کاربران محصول شما را به گزینه‌های دیگر ترجیح دهند. در این دوره با اصول مهم طراحی مانند وایرفریم، نمونه‌سازی (Prototype)،طراحی مسیر کاربر (User Flow)، ناوبری شفاف، دسترس‌پذیری و ساخت محصولاتی که یادگیری و استفاده از آن‌ها آسان باشد آشنا شدم.",
            "project": {
                "title": "پروژه دوره",
                "name": "برنامه حسابداری شخصی - طراحی UI/UX",
                "platform": "پلتفرم",
                "discription": "رابط کاربری یک اپلیکیشن مدیریت مالی شخصی واکنش گرا با استفاده از Figma طراحی کردم. تمرکز بر اصول طراحی کاربرمحور بود، شامل پیگیری درآمد و هزینه‌ها، مدیریت دسته‌بندی‌ها و نمایش گزارش‌ها.",
                "view": "نمایش پروژه",
                "acquired": "مفاهیم کسب شده",
                "1": "وایرفریم & پروتوتایپ",
                "2": "جرین کاربر & ناوبری",
                "3": "بهبود قابلیت استفاده",
                "4": "دسترسی پذیری"
            }
        },
        "experience": {
            "heading": "سابقه کار",
            "title": "مدیریت سایت وردپرس",
            "place": "گروه بازرگانی شهیدی - دی-آذر 1404",
            "1": "مدیریت و به‌روزرسانی محتوای وب‌سایت از طریق سیستم مدیریت محتوای وردپرس",
            "2": "نصب و پیکربندی قالب‌ها و افزونه‌ها",
            "3": "پیاده‌سازی اصول پایه سئو با استفاده از افزونه Yoast SEO",
            "4": "عیب‌یابی و رفع مشکلات از طریق پنل مدیریت وردپرس",
            "5": "طراحی صفحات ریسپانسیو با استفاده از Elementor",
            "focuse": "تمرکز فعلی",
            "discription": "در حال گذار به توسعه مدرن فرانت‌اند با استفاده از React، Next.js، TypeScript و Tailwind از طریق پروژه‌های شخصی."
        }
    },
    "skils": {
        "heading": "مهارت ها",
        "1": {
            "title": "فرانت اند",
            "item1": "JavaScript, Next.js, React, TypeScript",
            "item2": "HTML, CSS, Tailwind, Responsive Design, REST API"
        },
        "2": {
            "title": "UI/UX و طراحی",
            "item": "Figma, UX/UI, Wireframing, Prototyping"
        },
        "3": {
            "title": "ابزار",
            "iems": "Git, Postman, WordPress, Adobe Photoshop, Adobe Illustrator, Adobe Premiere"
        }
    },
    "projects": {
        "heading" : "پروژه ها"
    },
    "contact": {
        "city": "تهران",
        "born": "تولد",
        "date": "1374/06/18"
    },
    "card":{
        "todo" : {
            "title": "لیست وظایف",
            "discription": "یک اپلیکیشن مدیریت وظایف فول‌استک با احراز هویت امن، مدیریت تسک‌های اختصاصی هر کاربر، قابلیت جستجو و فیلتر، دسته‌بندی، و عملیات کامل CRUD همراه با ذخیره‌سازی پایدار داده‌ها."
        },
        "dashboard": {
            "title": "داشبورد",
            "discription": "داشبورد مدیریت فروشگاه اینترنتی برای مدیریت کاربران، مشتریان، سفارش‌ها و درآمد با استفاده از React و Next.js."
        }
    },
    "todoApp": {
        "header": "لیست وظایف",
        "title": "اپلیکیشن مدیریت وظایف فول‌استک",
        "demo": "نمایش پروژه",
        "account": "حساب آزمایشی:",
        "emial": "Email",
        "pass": "passwoard",
        "github": "GitHub Repository"
    },
    "overview": {
        "title": "نمای کلی",
        "discription": "این یک اپلیکیشن مدیریت وظایف فول‌استک است که با Next.js و Supabase ساخته شده است و به کاربران امکان احراز هویت امن، مدیریت تسک‌های شخصی خود و تعامل با یک دیتابیس پایدار را می‌دهد و تمرکز آن بر طراحی رابط کاربری تمیز و طراحی ریسپانسیو بوده است."
    },
    "features":{
        "title": "ویژگی‌های کلیدی",
        "1": "احراز هویت امن کاربران",
        "2": "مدیریت تسک‌های اختصاصی هر کاربر",
        "3": "ایجاد، ویرایش، حذف و بروزرسانی تسک‌ها (CRUD)",
        "4": "قابلیت جستجو و فیلتر",
        "5": "دسته‌بندی تسک‌ها",
        "6": "ذخیره‌سازی پایدار در دیتابیس",
        "7": "طراحی کاملاً ریسپانسیو"
    },
    "challenge": {
        "title": "چالش ها",
        "discription": "یکی از چالش‌های اصلی، پیکربندی Providerهای NextAuth و مدیریت یکپارچه احراز هویت در محیط‌های کلاینت‌ساید و سرور‌ساید بود که نیازمند مدیریت صحیح سشن‌ها و پیاده‌سازی منطق محافظت از مسیرها (Protected Routes) بود."
    }
}